Workbook

Sheet 封面
B2: KAIYI · 开瑞汽车
B3: 海外营销 H5 项目年度报价单
B4: QUOTATION / 2026–2027
B7: 项 目 概 述
B8: 项目名称 | C8: KAIYI · Share Your Destination 海外品牌营销 H5
B9: 客户单位 | C9: KAIYI 开瑞汽车（海外事业部）
B10: 项目周期 | C10: 2026 年 9 月 — 2027 年 8 月（12 个月）
B11: 交付形态 | C11: 移动端 H5（Vite + React）+ PC 桌面端响应式适配
B12: 适配设备 | C12: PC 桌面浏览器（≥ 1024px）+ 移动端（≤ 768px）双端自适应
B13: 分享渠道 | C13: Facebook · Instagram（系统分享面板带图分享）
B14: 核心能力 | C14: 12 个月度主题自动切换 · 3 款相框模板 · 图片生成 · 一键分享
B15: 维护模式 | C15: 每月 1 套新模板（设计 + 开发 + 上线）
B16: 文档版本 | C16: V1.1 / 2026-09-08 / 人民币报价 · 含 PC + 移动端
B18: 报 价 汇 总
B19: A. 一次性设计费 | F19: =报价明细!E5
B20: B. 一次性开发费 | F20: =报价明细!E13
B21: C. 项目管理 / 客户确认 | F21: =报价明细!E18
B22: D. 月度维护费（12 个月） | F22: =报价明细!H6
B23: E. 托管 / 空间 / 域名（年度） | F23: =报价明细!H11
B24: F. 运营服务费（年度） | F24: =报价明细!H15
B25: G. 增值税（6%） | F25: =报价明细!H19
B26: 合计（含税） | F26: =报价明细!H22
F27: =报价明细!H25
B28: 报价有效期：自本报价单签发之日起 30 个自然日 / 报价单位：人民币元（CNY） / 含 6% 增值税

Sheet 报价明细
A1: 序号 | B1: 项目名称 | C1: 工作内容 / 交付物 | D1: 数量 | E1: 单价 (¥) | F1: 说明 / 工艺要点 | G1: 计量 | H1: 小计 (¥)
A2: A. 一次性设计费（Design）
A3: 1 | B3: 主题视觉系统设计 | C3: 12 个月主题色板、字体、版式风格指南（Design Guideline） | D3: 1 | E3: 30000 | F3: 逐月差异化，确保全年品牌调性一致 | G3: 套 | H3: =D3*E3
A4: 2 | B4: 相框模板设计 | C4: 3 款相框 × 12 个月 = 36 款原创版式（路线打卡 / 旅行明信片 / 车窗视角） | D4: 36 | E4: 1200 | F4: 每款含 PC + 移动端双端 3:4 出图样式 + 月度文案 + 装饰图标 | G4: 款 | H4: =D4*E4
A5: 3 | B5: SVG 图标系统 | C5: 12 个季节 / 主题线性图标（currentColor） | D5: 12 | E5: 600 | F5: 可在 html2canvas / html-to-image 安全截图 | G5: 个 | H5: =D5*E5
A6: 4 | B6: PWA 应用图标 | C6: icon.svg + icon-maskable.svg + 启动画面 | D6: 1 | E6: 3000 | F6: 支持添加到主屏幕 / 桌面图标 | G6: 套 | H6: =D6*E6
A7: 5 | B7: 品牌首页 / 任务弹窗视觉 | C7: 首页主视觉 12 套 + 任务弹窗 12 套视觉稿 | D7: 24 | E7: 800 | F7: PC + 移动端双端布局，含文案层级、按钮态、动效指引 | G7: 套 | H7: =D7*E7
B8: A 小计（一次性设计费） | H8: =SUM(H3:H7)
A10: B. 一次性开发费（Development）
A11: 1 | B11: H5 主框架开发 | C11: Vite + React + PC/移动端响应式适配 + Vercel 全球托管 | D11: 1 | E11: 25000 | F11: PC 桌面（≥1024px）+ 移动端（≤768px）双端自适应，PWA Manifest、Service Worker、Lighthouse 95+ | G11: 套 | H11: =D11*E11
A12: 2 | B12: 四大流程页面 | C12: 品牌首页 / 月度任务弹窗 / 模板创作 / 一键分享 | D12: 4 | E12: 4500 | F12: PC + 移动端双端适配，含路由、状态管理、断点响应式 | G12: 页 | H12: =D12*E12
A13: 3 | B13: 图片生成与系统分享 | C13: html-to-image 截图 + Web Share API（带文件）+ FB/IG 面板调起 | D13: 1 | E13: 12000 | F13: 支持 Facebook / Instagram App 一键带图分享 | G13: 套 | H13: =D13*E13
A14: 4 | B14: 月度主题引擎 | C14: 12 个月主题切换 + 全年主题画廊 + 每月差异化文案注入 | D14: 1 | E14: 8000 | F14: 数据驱动：themes.js 一处维护全局生效 | G14: 套 | H14: =D14*E14
A15: 5 | B15: PWA / 缓存 / 离线 | C15: 离线访问、添加到主屏、桌面图标、安装提示 | D15: 1 | E15: 5000 | F15: 提升海外用户访问体验 | G15: 套 | H15: =D15*E15
B16: B 小计（一次性开发费） | H16: =SUM(H11:H15)
A18: C. 项目管理与客户确认（PM & UAT）
A19: 1 | B19: 需求梳理 / 方案设计 | C19: 业务调研、用户旅程、信息架构、流程图 | D19: 1 | E19: 6000 | F19: 输出 PRD / 原型 / 验收标准 | G19: 套 | H19: =D19*E19
A20: 2 | B20: 客户确认 / 版本评审 | C20: 三轮视觉 + 功能评审会（含会议纪要、修订意见落地） | D20: 3 | E20: 3000 | F20: 保障上线即验收通过 | G20: 轮 | H20: =D20*E20
A21: 3 | B21: UAT 验收与上线 | C21: 测试用例、回归测试、生产部署、域名备案支持 | D21: 1 | E21: 6000 | F21: 覆盖 12 个月度主题上线 | G21: 次 | H21: =D21*E21
B22: C 小计（项目管理 / 客户确认） | H22: =SUM(H19:H21)
A24: D. 月度维护费（按月续约 · 12 个月）
A25: 1 | B25: 每月新模板设计 | C25: 1 套新相框版式（含 3:4 出图 + 文案 + 图标） | D25: 12 | E25: 5000 | F25: 保持月度内容新鲜度 | G25: 月 | H25: =D25*E25
A26: 2 | B26: 主题内容更新 | C26: 月度标题、标语、话题标签、品牌色、文案 | D26: 12 | E26: 3000 | F26: 数据驱动更新 themes.js 一处生效 | G26: 月 | H26: =D26*E26
A27: 3 | B27: 上线部署 / 回归 | C27: 新模板上线 + 回归测试 + 旧模板兼容性检查 | D27: 12 | E27: 2000 | F27: 确保零中断发布 | G27: 月 | H27: =D27*E27
B28: D 小计（月度维护 × 12 月） | H28: =SUM(H25:H27)
A30: E. 托管 / 空间 / 域名（年度）
A31: 1 | B31: Vercel Pro 托管 | C31: 全球 CDN · 自动 HTTPS · 预览部署 · 99.99% SLA | D31: 1 | E31: 2400 | F31: 覆盖海外多区域访问 | G31: 年 | H31: =D31*E31
A32: 2 | B32: 域名注册 / 维护 | C32: .com / .life / .moto 等海外品牌域名 | D32: 1 | E32: 500 | F32: 首年注册 + WHOIS 隐私保护 | G32: 年 | H32: =D32*E32
A33: 3 | B33: SSL / DNS 配置 | C33: 证书托管 + DNS 解析优化 | D33: 1 | E33: 0 | F33: Vercel 自动签发，含在托管费内 | G33: 年 | H33: =D33*E33
B34: E 小计（托管 / 空间 / 域名） | H34: =SUM(H31:H33)
A36: F. 运营服务费（年度）
A37: 1 | B37: 内容运营支持 | C37: 话题策划、文案润色、多语言适配（含英 / 西 / 阿） | D37: 12 | E37: 1500 | F37: 覆盖海外三大主要市场 | G37: 月 | H37: =D37*E37
A38: 2 | B38: 数据监控 / 月报 | C38: UV / 分享率 / 月度活跃 / 转化漏斗 + 报告 | D38: 12 | E38: 1500 | F38: 每月 1 份数据报告 + 优化建议 | G38: 月 | H38: =D38*E38
A39: 3 | B39: 客户活动支持 | C39: 节日 / 营销节点 / 联合活动素材快速响应 | D39: 4 | E39: 3000 | F39: 每季度 1 次专项活动 | G39: 次 | H39: =D39*E39
B40: F 小计（运营服务） | H40: =SUM(H37:H39)
A42: 项目总计（含税前 · 不含增值税） | H42: =H6+H11+H15+H19+H22+H25

Sheet 月度计划
A1: 月份 | B1: 主题 | C1: 核心话题 / Hashtag | D1: 相框模板版本 | E1: 上线日期 | F1: 维护项
A2: 9 | B2: Share Your Destination | C2: #KaiyiLifeInMotion · #ShareYourDestination | D2: v1.0（首发 3 款） | E2: 2026-09-15 | F2: 首发上线 + 客户验收
A3: 10 | B3: Autumn Colors | C3: #AutumnColors · #KaiyiLifeInMotion | D3: v1.1（新增 1 款） | E3: 2026-10-15 | F3: 月度新模板 + 主题更新
A4: 11 | B4: Misty Lake | C4: #MistyLake · #KaiyiLifeInMotion | D4: v1.2 | E4: 2026-11-15 | F4: 月度新模板 + 主题更新
A5: 12 | B5: Winter Wonderland | C5: #WinterWonderland | D5: v1.3 | E5: 2026-12-15 | F5: 节日活动支持
A6: 1 | B6: New Year Drive | C6: #NewYearDrive | D6: v1.4 | E6: 2027-01-15 | F6: 新年活动专题
A7: 2 | B7: Valentine Ride | C7: #ValentineRide | D7: v1.5 | E7: 2027-02-14 | F7: 情人节专题
A8: 3 | B8: Spring Bloom | C8: #SpringBloom | D8: v1.6 | E8: 2027-03-15 | F8: 春日主题
A9: 4 | B9: Cherry Road | C9: #CherryRoad | D9: v1.7 | E9: 2027-04-15 | F9: 樱花季专题
A10: 5 | B10: Coastal Drift | C10: #CoastalDrift | D10: v1.8 | E10: 2027-05-15 | F10: 海岸线主题
A11: 6 | B11: Desert Light | C11: #DesertLight | D11: v1.9 | E11: 2027-06-15 | F11: 沙漠光线主题
A12: 7 | B12: Highland Pass | C12: #HighlandPass | D12: v2.0 | E12: 2027-07-15 | F12: 高地穿越 + 半年度回顾
A13: 8 | B13: Sunset Mile | C13: #SunsetMile | D13: v2.1 | E13: 2027-08-15 | F13: 年度收官 + 数据复盘
A15: 12 个月维护 + 运营 · 小计 | F15: =报价明细!H19+报价明细!H25

Sheet 服务条款
A1: 服 务 条 款 与 付 款 说 明
B2: 条款类别 | C2: 具体内容
B3: 项目周期 | C3: 本项目合同周期为 12 个月，自双方签署之日起生效，到期前 30 日协商续约。
B4: 交付物清单 | C4: （1）H5 主程序（含源码，PC + 移动端双端响应式）；（2）12 套主题视觉稿；（3）36 款相框模板；（4）月度维护 12 次；（5）Vercel 全球托管 + 域名；（6）月度数据报告 × 12。
B5: 一次性付款 | C5: A + B + C 项合计一次性付款 50%，项目启动 5 个工作日内支付；上线验收后 30 日内支付 50% 尾款。
B6: 月度付款 | C6: D + F 项按月支付，每月 5 日前开具上月发票并收款；E 项年度费用首次部署时一次性支付。
B7: 知识产权 | C7: 项目交付物的著作权归乙方所有；甲方拥有本项目专属永久使用权；乙方可在作品集中展示。
B8: 客户配合 | C8: 甲方应在 5 个工作日内反馈确认意见；超期未反馈视为默认通过确认。每自然月最多发起 2 次模板修订。
B9: 维保范围 | C9: 免费维保期 12 个月，含 Bug 修复、依赖升级、安全补丁；新功能 / 新主题属月度维护范围。
B10: 变更管理 | C10: 需求变更需双方书面确认；超出原范围的工作量按 1,500 元 / 人天单独计费。
B11: 数据合规 | C11: 项目遵守 GDPR 与目标市场数据法规；用户上传图片仅本地处理，不上传服务器。
B12: 终止条款 | C12: 任意一方可提前 30 日书面通知终止合同；已交付部分按比例结算，未交付部分退还未发生款项。
B13: 争议解决 | C13: 本协议适用中华人民共和国法律；争议提交项目所在地人民法院诉讼解决。
B14: 报价有效期 | C14: 自签发之日起 30 个自然日内有效。

Sheet 联系信息
A1: 联 系 方 式
B3: 委托方（甲方） | E3: 受托方（乙方）
B4: 客户单位 | C4: KAIYI 开瑞汽车 | E4: 服务商 | F4: 彩讯科技股份有限公司
B5: 联系人 | C5: 海外事业部 | E5: 联系人 | F5: 项目商务部
B6: 邮箱 | C6: marketing@KAIYI-global.com | E6: 邮箱 | F6: biz@caixun.com
B7: 电话 | C7: +86 10-XXXX XXXX | E7: 电话 | F7: +86 10-XXXX XXXX
B8: 地址 | C8: 北京市朝阳区 XX 大厦 | E8: 地址 | F8: 深圳市南山区 XX 大厦
B10: 感谢您的信任，期待携手共创 KAIYI 海外品牌新篇章！
